{"coauthorstat":[{"coauthor":"Daniel Ferr&eacute;s","num":16,"ID":104},{"coauthor":"Alicia Ageno","num":6,"ID":446},{"coauthor":"Jordi Turmo","num":4,"ID":103},{"coauthor":"Samir Kanaan","num":4,"ID":627},{"coauthor":"Edgar Gonz&aacute;lez","num":4,"ID":712}],"yearstat":[{"year":"2004","num":2},{"year":"2005","num":4},{"year":"2006","num":2},{"year":"2007","num":4},{"year":"2008","num":1},{"year":"2009","num":2},{"year":"2010","num":1},{"year":"2011","num":0},{"year":"2012","num":0},{"year":"2013","num":0},{"year":"2014","num":0},{"year":"2015","num":1},{"year":"2016","num":1}]}